[
  {
    "expansionId": "A4",
    "name": "The Golden Sky, where Ho-Oh Soars",
    "requiredCards": [],
    "reward": "Emblem Ticket (Wisdom of Sea and Sky) ×19"
  },
  {
    "expansionId": "A4",
    "name": "The Silvery Ocean, where Lugia Dwells",
    "requiredCards": [],
    "reward": "Emblem Ticket (Wisdom of Sea and Sky) ×20"
  },
  {
    "expansionId": "A4",
    "name": "Pokémon that can Use Attacks Immediately",
    "requiredCards": [],
    "reward": "Emblem Ticket (Wisdom of Sea and Sky) ×12"
  },
  {
    "expansionId": "A4",
    "name": "Shapes that Resemble Ancient Writing",
    "requiredCards": [
      {
        "options": ["A4-84"],
        "amount": 1
      },
      {
        "options": ["A4-85"],
        "amount": 1
      }
    ],
    "reward": "Emblem Ticket (Wisdom of Sea and Sky) ×6"
  },
  {
    "expansionId": "A4",
    "name": "Staying Still...",
    "requiredCards": [],
    "reward": "Emblem Ticket (Wisdom of Sea and Sky) ×3"
  },
  {
    "expansionId": "A4",
    "name": "The Man in the Mysterious Mask",
    "requiredCards": [],
    "reward": "Emblem Ticket (Wisdom of Sea and Sky) ×2"
  },
  {
    "expansionId": "A4",
    "name": "The Steel-Clad-Defense Girl",
    "requiredCards": [],
    "reward": "Emblem Ticket (Wisdom of Sea and Sky) ×8"
  },
  {
    "expansionId": "A4",
    "name": "Lake of Rage",
    "requiredCards": [
      {
        "options": ["A4-44"],
        "amount": 4
      },
      {
        "options": ["A4-215"],
        "amount": 1
      }
    ],
    "reward": "Emblem Ticket (Wisdom of Sea and Sky) ×5"
  },
  {
    "expansionId": "A4",
    "name": "A Mass Outbreak of Pokémon",
    "requiredCards": [],
    "reward": "Wonder Hourglass ×12<br />Emblem Ticket (Wisdom of Sea and Sky) ×2<br />Shop Ticket ×2"
  },
  {
    "expansionId": "A4",
    "name": "Pokémon you Meet at the National Park",
    "requiredCards": [],
    "reward": "Wonder Hourglass ×12<br />Emblem Ticket (Wisdom of Sea and Sky) ×1<br />Shop Ticket ×2"
  },
  {
    "expansionId": "A4",
    "name": "Journeying with a Partner and an Egg",
    "requiredCards": [
      {
        "amount": "1",
        "options": []
      }
    ],
    "reward": "Wonder Hourglass ×12<br />Emblem Ticket (Wisdom of Sea and Sky) ×1<br />Shop Ticket ×2"
  },
  {
    "expansionId": "A4",
    "name": "A Delivery of Presents for Everyone",
    "requiredCards": [
      {
        "options": ["A4-170"],
        "amount": 1
      }
    ],
    "reward": "Emblem Ticket (Wisdom of Sea and Sky) ×6"
  },
  {
    "expansionId": "A4",
    "name": "Vibrant Petals",
    "requiredCards": [],
    "reward": "Emblem Ticket (Wisdom of Sea and Sky) ×4"
  },
  {
    "expansionId": "A4",
    "name": "They have Two Faces?",
    "requiredCards": [
      {
        "options": ["A4-86"],
        "amount": 1
      },
      {
        "options": ["A4-110"],
        "amount": 1
      }
    ],
    "reward": "Wonder Hourglass ×12<br />Emblem Ticket (Wisdom of Sea and Sky) ×1<br />Shop Ticket ×2"
  },
  {
    "expansionId": "A4",
    "name": "Hard, Body-Protecting Shells",
    "requiredCards": [],
    "reward": "Wonder Hourglass ×12<br />Emblem Ticket (Wisdom of Sea and Sky) ×1<br />Shop Ticket ×2"
  },
  {
    "expansionId": "A4",
    "name": "Large Horns Brimming with Charm",
    "requiredCards": [],
    "reward": "Emblem Ticket (Wisdom of Sea and Sky) ×3"
  },
  {
    "expansionId": "A4",
    "name": "Remoraid, Clinging to a Fin",
    "requiredCards": [],
    "reward": "Wonder Hourglass ×12<br />Emblem Ticket (Wisdom of Sea and Sky) ×1<br />Shop Ticket ×2"
  },
  {
    "expansionId": "A4",
    "name": "Hiking: Discovery and Exploration",
    "requiredCards": [],
    "reward": "Wonder Hourglass ×12<br />Emblem Ticket (Wisdom of Sea and Sky) ×2<br />Shop Ticket ×2"
  },
  {
    "expansionId": "A4",
    "name": "Fishing for a Big Catch",
    "requiredCards": [
      {
        "options": ["A4-44"],
        "amount": 1
      }
    ],
    "reward": "Wonder Hourglass ×12<br />Emblem Ticket (Wisdom of Sea and Sky) ×2<br />Shop Ticket ×2"
  },
  {
    "expansionId": "A4",
    "name": "Collect 5 Meganium cards",
    "requiredCards": [],
    "reward": "Meganium (icon)"
  },
  {
    "expansionId": "A4",
    "name": "Collect 5 Typhlosion cards",
    "requiredCards": [],
    "reward": "Typhlosion (icon)"
  },
  {
    "expansionId": "A4",
    "name": "Collect 5 Feraligatr cards",
    "requiredCards": [],
    "reward": "Feraligatr (icon)"
  },
  {
    "expansionId": "A4",
    "name": "Illustrated Pokémon Handscrolls",
    "requiredCards": [
      {
        "options": ["A4-168"],
        "amount": 1
      },
      {
        "options": ["A4-183"],
        "amount": 1
      }
    ],
    "reward": "Wonder Hourglass ×36<br />Pack Hourglass ×12<br />Shop Ticket ×10"
  },
  {
    "expansionId": "A4",
    "name": "Wisdom of Sea and Sky Museum 1",
    "requiredCards": [
      {
        "options": ["A4-164"],
        "amount": 1
      },
      {
        "options": ["A4-166"],
        "amount": 1
      },
      {
        "options": ["A4-167"],
        "amount": 1
      },
      {
        "options": ["A4-170"],
        "amount": 1
      },
      {
        "options": ["A4-173"],
        "amount": 1
      },
      {
        "options": ["A4-176"],
        "amount": 1
      },
      {
        "options": ["A4-177"],
        "amount": 1
      },
      {
        "options": ["A4-179"],
        "amount": 1
      },
      {
        "options": ["A4-181"],
        "amount": 1
      },
      {
        "options": ["A4-182"],
        "amount": 1
      },
      {
        "options": ["A4-183"],
        "amount": 1
      },
      {
        "options": ["A4-185"],
        "amount": 1
      }
    ],
    "reward": "Wonder Hourglass ×36<br />Pack Hourglass ×12<br />Shop Ticket ×10"
  },
  {
    "expansionId": "A4",
    "name": "Wisdom of Sea and Sky Museum 2",
    "requiredCards": [
      {
        "options": ["A4-162"],
        "amount": 1
      },
      {
        "options": ["A4-163"],
        "amount": 1
      },
      {
        "options": ["A4-165"],
        "amount": 1
      },
      {
        "options": ["A4-168"],
        "amount": 1
      },
      {
        "options": ["A4-169"],
        "amount": 1
      },
      {
        "options": ["A4-171"],
        "amount": 1
      },
      {
        "options": ["A4-172"],
        "amount": 1
      },
      {
        "options": ["A4-174"],
        "amount": 1
      },
      {
        "options": ["A4-175"],
        "amount": 1
      },
      {
        "options": ["A4-178"],
        "amount": 1
      },
      {
        "options": ["A4-180"],
        "amount": 1
      },
      {
        "options": ["A4-184"],
        "amount": 1
      }
    ],
    "reward": "Wonder Hourglass ×36<br />Pack Hourglass ×12<br />Shop Ticket ×10"
  },
  {
    "expansionId": "A4",
    "name": "Wisdom of Sea and Sky Museum 3",
    "requiredCards": [
      {
        "options": ["A4-206"],
        "amount": 1
      },
      {
        "options": ["A4-207"],
        "amount": 1
      },
      {
        "options": ["A4-208"],
        "amount": 1
      },
      {
        "options": ["A4-209"],
        "amount": 1
      }
    ],
    "reward": "Wonder Hourglass ×36<br />Pack Hourglass ×12<br />Shop Ticket ×10"
  },
  {
    "expansionId": "A4",
    "name": "Wisdom of Sea and Sky Museum 4",
    "requiredCards": [
      {
        "options": ["A4-202"],
        "amount": 1
      },
      {
        "options": ["A4-203"],
        "amount": 1
      },
      {
        "options": ["A4-204"],
        "amount": 1
      },
      {
        "options": ["A4-205"],
        "amount": 1
      }
    ],
    "reward": "Wonder Hourglass ×36<br />Pack Hourglass ×12<br />Shop Ticket ×10"
  },
  {
    "expansionId": "A4",
    "name": "Smeargle's Colorful Collection",
    "requiredCards": [
      {
        "options": ["A4-162"],
        "amount": 1
      },
      {
        "options": ["A4-163"],
        "amount": 1
      },
      {
        "options": ["A4-164"],
        "amount": 1
      },
      {
        "options": ["A4-202"],
        "amount": 1
      },
      {
        "options": ["A4-165"],
        "amount": 1
      },
      {
        "options": ["A4-166"],
        "amount": 1
      },
      {
        "options": ["A4-167"],
        "amount": 1
      },
      {
        "options": ["A4-168"],
        "amount": 1
      },
      {
        "options": ["A4-169"],
        "amount": 1
      },
      {
        "options": ["A4-170"],
        "amount": 1
      },
      {
        "options": ["A4-203"],
        "amount": 1
      },
      {
        "options": ["A4-171"],
        "amount": 1
      },
      {
        "options": ["A4-172"],
        "amount": 1
      },
      {
        "options": ["A4-204"],
        "amount": 1
      },
      {
        "options": ["A4-173"],
        "amount": 1
      },
      {
        "options": ["A4-174"],
        "amount": 1
      },
      {
        "options": ["A4-175"],
        "amount": 1
      },
      {
        "options": ["A4-205"],
        "amount": 1
      },
      {
        "options": ["A4-176"],
        "amount": 1
      },
      {
        "options": ["A4-206"],
        "amount": 1
      },
      {
        "options": ["A4-177"],
        "amount": 1
      },
      {
        "options": ["A4-178"],
        "amount": 1
      },
      {
        "options": ["A4-179"],
        "amount": 1
      },
      {
        "options": ["A4-207"],
        "amount": 1
      },
      {
        "options": ["A4-208"],
        "amount": 1
      },
      {
        "options": ["A4-180"],
        "amount": 1
      },
      {
        "options": ["A4-209"],
        "amount": 1
      },
      {
        "options": ["A4-181"],
        "amount": 1
      },
      {
        "options": ["A4-182"],
        "amount": 1
      },
      {
        "options": ["A4-103"],
        "amount": 1
      },
      {
        "options": ["A4-185"],
        "amount": 1
      },
      {
        "options": ["A4-184"],
        "amount": 1
      }
    ],
    "reward": "Smeargle"
  }
]
